eagle_eye_scraper/__init__.py
eagle_eye_scraper/com/__init__.py
eagle_eye_scraper/com/domains.py
eagle_eye_scraper/com/config/__init__.py
eagle_eye_scraper/com/config/env_config.py
eagle_eye_scraper/com/constant/__init__.py
eagle_eye_scraper/com/constant/mq_constant.py
eagle_eye_scraper/com/db/__init__.py
eagle_eye_scraper/com/db/minio.py
eagle_eye_scraper/com/db/mongo.py
eagle_eye_scraper/com/db/mysql.py
eagle_eye_scraper/com/db/pulsar.py
eagle_eye_scraper/com/db/redis.py
eagle_eye_scraper/com/mq/__init__.py
eagle_eye_scraper/com/mq/pullsar/__init__.py
eagle_eye_scraper/com/mq/pullsar/messages.py
eagle_eye_scraper/com/mq/ram/__init__.py
eagle_eye_scraper/com/mq/ram/messages.py
eagle_eye_scraper/com/mq/ram/priority_queues.py
eagle_eye_scraper/com/mq/ram/ram_mq.py
eagle_eye_scraper/com/utils/__init__.py
eagle_eye_scraper/com/utils/log.py
eagle_eye_scraper/com/utils/string_utils.py
eagle_eye_scraper/com/utils/time_util.py
eagle_eye_scraper/core/__init__.py
eagle_eye_scraper/core/spider.py
eagle_eye_scraper/dispatch/__init__.py
eagle_eye_scraper/dispatch/dispatcher_selector.py
eagle_eye_scraper/dispatch/host_dispatcher.py
eagle_eye_scraper/dispatch/pulsar_dispatcher.py
eagle_eye_scraper/dispatch/ram_dispatcher.py
eagle_eye_scraper/repository/__init__.py
eagle_eye_scraper/repository/mongo/__init__.py
eagle_eye_scraper/repository/mongo/helpers.py
eagle_eye_scraper/repository/mysql/__init__.py
eagle_eye_scraper/repository/mysql/helpers.py
eagle_eye_scraper/repository/mysql/session_factory.py
eagle_eye_scraper/scheduler_visual/__init__.py
eagle_eye_scraper/scheduler_visual/scheduler.py
eagle_eye_scraper/scheduler_visual/schema.py
eagle_eye_scraper/scheduler_visual/shared.py
eagle_eye_scraper/scheduler_visual/visual_application.py
eagle_eye_scraper/scheduler_visual/router/__init__.py
eagle_eye_scraper/scheduler_visual/router/executor_router.py
eagle_eye_scraper/scheduler_visual/router/job_router.py
eagle_eye_scraper/scheduler_visual/router/log_router.py
eagle_eye_scraper-1.3.6.dist-info/LICENSE
eagle_eye_scraper-1.3.6.dist-info/METADATA
eagle_eye_scraper-1.3.6.dist-info/WHEEL
eagle_eye_scraper-1.3.6.dist-info/top_level.txt
eagle_eye_scraper-1.3.6.dist-info/RECORD
