Metadata-Version: 2.1
Name: eagle-eye-scraper
Version: 1.3.6
Summary: eagle-eye-scraper 是一个高效的 Python 数据采集框架，支持分布式部署，适用于复杂页面和大规模数据采集。
Author-email: Nick <mr.nickdone@gmail.com>
License: MIT License
Keywords: python,scraper,data extraction,distributed scraping
Classifier: Programming Language :: Python :: 3
Classifier: Programming Language :: Python :: 3.8
Classifier: License :: OSI Approved :: MIT License
Classifier: Operating System :: OS Independent
Classifier: Topic :: Internet :: WWW/HTTP :: Indexing/Search
Classifier: Intended Audience :: Developers
Classifier: Intended Audience :: Science/Research
Classifier: Development Status :: 4 - Beta
Requires-Python: >=3.8
License-File: LICENSE
Requires-Dist: APScheduler==3.10.4
Requires-Dist: pydantic==2.10.6
Requires-Dist: PyYAML==6.0.2
Requires-Dist: fastapi==0.115.6
Requires-Dist: fastui==0.7.0
Requires-Dist: uvicorn==0.30.6
Provides-Extra: minio
Requires-Dist: minio==7.1.13; extra == "minio"
Provides-Extra: mongodb
Requires-Dist: mongoengine==0.27.0; extra == "mongodb"
Requires-Dist: pymongo==4.6.3; extra == "mongodb"
Provides-Extra: mq
Requires-Dist: pulsar-client==3.5.0; extra == "mq"
Provides-Extra: mysql
Requires-Dist: PyMySQL==0.9.2; extra == "mysql"
Requires-Dist: SQLAlchemy==1.4.54; extra == "mysql"
Provides-Extra: redis
Requires-Dist: redis==6.1.1; extra == "redis"
